{
  "channel_name": "Colors Gujarati Cinema",
  "channel_logo": "https://jiotv.catchup.cdn.jio.com/dare_images/images/Colors_Gujarati_Cinema.png",
  "date": "2025-12-05",
  "programs": [
    {
      "show_name": "Mara Sayaba Ni Chundadi",
      "start_time": "12:00 AM",
      "end_time": "12:45 AM",
      "show_logo": "https://jiotv.catchup.cdn.jio.com/dare_images/shows/2025-12-05/2512051324000.jpg"
    },
    {
      "show_name": "Prithviraj Sanyukta",
      "start_time": "12:45 AM",
      "end_time": "02:50 AM",
      "show_logo": "https://jiotv.catchup.cdn.jio.com/dare_images/shows/2025-12-05/2512051324001.jpg"
    },
    {
      "show_name": "Deshi Beats",
      "start_time": "02:50 AM",
      "end_time": "05:40 AM",
      "show_logo": "https://jiotv.catchup.cdn.jio.com/dare_images/shows/2025-12-05/2512051324002.jpg"
    },
    {
      "show_name": "Khoradani Laaj Wahune Haath",
      "start_time": "05:40 AM",
      "end_time": "08:00 AM",
      "show_logo": "https://jiotv.catchup.cdn.jio.com/dare_images/shows/2025-12-05/2512051324003.jpg"
    },
    {
      "show_name": "Deshi Beats",
      "start_time": "08:00 AM",
      "end_time": "10:15 AM",
      "show_logo": "https://jiotv.catchup.cdn.jio.com/dare_images/shows/2025-12-05/2512051324004.jpg"
    },
    {
      "show_name": "Parshuram",
      "start_time": "10:15 AM",
      "end_time": "01:20 PM",
      "show_logo": "https://jiotv.catchup.cdn.jio.com/dare_images/shows/2025-12-05/2512051324005.jpg"
    },
    {
      "show_name": "VAGYA PRITYU NA DHOL",
      "start_time": "01:20 PM",
      "end_time": "04:20 PM",
      "show_logo": "https://jiotv.catchup.cdn.jio.com/dare_images/shows/2025-12-05/2512051324006.jpg"
    },
    {
      "show_name": "Raakh Na Ramakda",
      "start_time": "04:20 PM",
      "end_time": "07:00 PM",
      "show_logo": "https://jiotv.catchup.cdn.jio.com/dare_images/shows/2025-12-05/2512051324007.jpg"
    },
    {
      "show_name": "Dada Ho Dikri",
      "start_time": "07:00 PM",
      "end_time": "09:35 PM",
      "show_logo": "https://jiotv.catchup.cdn.jio.com/dare_images/shows/2025-12-05/2512051324008.jpg"
    },
    {
      "show_name": "Narmada Tara Vahi Jata Paani",
      "start_time": "09:35 PM",
      "end_time": "11:59 PM",
      "show_logo": "https://jiotv.catchup.cdn.jio.com/dare_images/shows/2025-12-05/2512051324009.jpg"
    }
  ]
}