{
  "channel_name": "Food Food",
  "channel_logo": "https://jiotv.catchup.cdn.jio.com/dare_images/images/Food_Food.png",
  "date": "2025-11-29",
  "programs": [
    {
      "show_name": "Mummy Ka Magic",
      "start_time": "12:00 AM",
      "end_time": "12:30 AM",
      "show_logo": "https://jiotv.catchup.cdn.jio.com/dare_images/shows/2025-11-29/251129561000.jpg"
    },
    {
      "show_name": "Sizzling Dal",
      "start_time": "12:30 AM",
      "end_time": "12:40 AM",
      "show_logo": "https://jiotv.catchup.cdn.jio.com/dare_images/shows/2025-11-29/251129561001.jpg"
    },
    {
      "show_name": "Vegan Vibes",
      "start_time": "12:40 AM",
      "end_time": "12:50 AM",
      "show_logo": "https://jiotv.catchup.cdn.jio.com/dare_images/shows/2025-11-29/251129561002.jpg"
    },
    {
      "show_name": "Dairy Delights",
      "start_time": "12:50 AM",
      "end_time": "01:00 AM",
      "show_logo": "https://jiotv.catchup.cdn.jio.com/dare_images/shows/2025-11-29/251129561003.jpg"
    },
    {
      "show_name": "Firangi Tadka",
      "start_time": "01:00 AM",
      "end_time": "01:30 AM",
      "show_logo": "https://jiotv.catchup.cdn.jio.com/dare_images/shows/2025-11-29/251129561004.jpg"
    },
    {
      "show_name": "Tea Time",
      "start_time": "01:30 AM",
      "end_time": "02:00 AM",
      "show_logo": "https://jiotv.catchup.cdn.jio.com/dare_images/shows/2025-11-29/251129561005.jpg"
    },
    {
      "show_name": "Turban Tadka",
      "start_time": "02:00 AM",
      "end_time": "02:30 AM",
      "show_logo": "https://jiotv.catchup.cdn.jio.com/dare_images/shows/2025-11-29/251129561006.jpg"
    },
    {
      "show_name": "Mummy Ka Magic",
      "start_time": "02:30 AM",
      "end_time": "03:00 AM",
      "show_logo": "https://jiotv.catchup.cdn.jio.com/dare_images/shows/2025-11-29/251129561007.jpg"
    },
    {
      "show_name": "Hi Tea",
      "start_time": "03:00 AM",
      "end_time": "03:30 AM",
      "show_logo": "https://jiotv.catchup.cdn.jio.com/dare_images/shows/2025-11-29/251129561008.jpg"
    },
    {
      "show_name": "Dairy Delights",
      "start_time": "03:30 AM",
      "end_time": "03:40 AM",
      "show_logo": "https://jiotv.catchup.cdn.jio.com/dare_images/shows/2025-11-29/251129561009.jpg"
    },
    {
      "show_name": "Bake Diaries",
      "start_time": "03:40 AM",
      "end_time": "03:50 AM",
      "show_logo": "https://jiotv.catchup.cdn.jio.com/dare_images/shows/2025-11-29/251129561010.jpg"
    },
    {
      "show_name": "Family Food Tales",
      "start_time": "03:50 AM",
      "end_time": "04:00 AM",
      "show_logo": "https://jiotv.catchup.cdn.jio.com/dare_images/shows/2025-11-29/251129561011.jpg"
    },
    {
      "show_name": "Hi Tea",
      "start_time": "04:00 AM",
      "end_time": "04:30 AM",
      "show_logo": "https://jiotv.catchup.cdn.jio.com/dare_images/shows/2025-11-29/251129561012.jpg"
    },
    {
      "show_name": "Cook Smart",
      "start_time": "04:30 AM",
      "end_time": "05:00 AM",
      "show_logo": "https://jiotv.catchup.cdn.jio.com/dare_images/shows/2025-11-29/251129561013.jpg"
    },
    {
      "show_name": "Turban Tadka",
      "start_time": "05:00 AM",
      "end_time": "05:30 AM",
      "show_logo": "https://jiotv.catchup.cdn.jio.com/dare_images/shows/2025-11-29/251129561014.jpg"
    },
    {
      "show_name": "Health Maange More",
      "start_time": "05:30 AM",
      "end_time": "06:00 AM",
      "show_logo": "https://jiotv.catchup.cdn.jio.com/dare_images/shows/2025-11-29/251129561015.jpg"
    },
    {
      "show_name": "Style Chef",
      "start_time": "06:00 AM",
      "end_time": "06:30 AM",
      "show_logo": "https://jiotv.catchup.cdn.jio.com/dare_images/shows/2025-11-29/251129561016.jpg"
    },
    {
      "show_name": "Health Maange More",
      "start_time": "06:30 AM",
      "end_time": "07:00 AM",
      "show_logo": "https://jiotv.catchup.cdn.jio.com/dare_images/shows/2025-11-29/251129561017.jpg"
    },
    {
      "show_name": "Sunny Side Up",
      "start_time": "07:00 AM",
      "end_time": "07:30 AM",
      "show_logo": "https://jiotv.catchup.cdn.jio.com/dare_images/shows/2025-11-29/251129561018.jpg"
    },
    {
      "show_name": "Firangi Tadka",
      "start_time": "07:30 AM",
      "end_time": "08:00 AM",
      "show_logo": "https://jiotv.catchup.cdn.jio.com/dare_images/shows/2025-11-29/251129561019.jpg"
    },
    {
      "show_name": "Cook Smart",
      "start_time": "08:00 AM",
      "end_time": "08:30 AM",
      "show_logo": "https://jiotv.catchup.cdn.jio.com/dare_images/shows/2025-11-29/251129561020.jpg"
    },
    {
      "show_name": "Only Veg",
      "start_time": "08:30 AM",
      "end_time": "09:30 AM",
      "show_logo": "https://jiotv.catchup.cdn.jio.com/dare_images/shows/2025-11-29/251129561021.jpg"
    },
    {
      "show_name": "Tea Time",
      "start_time": "09:30 AM",
      "end_time": "10:00 AM",
      "show_logo": "https://jiotv.catchup.cdn.jio.com/dare_images/shows/2025-11-29/251129561022.jpg"
    },
    {
      "show_name": "Firangi Tadka",
      "start_time": "10:00 AM",
      "end_time": "10:30 AM",
      "show_logo": "https://jiotv.catchup.cdn.jio.com/dare_images/shows/2025-11-29/251129561023.jpg"
    },
    {
      "show_name": "Vegan Vibes",
      "start_time": "10:30 AM",
      "end_time": "10:40 AM",
      "show_logo": "https://jiotv.catchup.cdn.jio.com/dare_images/shows/2025-11-29/251129561024.jpg"
    },
    {
      "show_name": "Winter Treats",
      "start_time": "10:40 AM",
      "end_time": "10:50 AM",
      "show_logo": "https://jiotv.catchup.cdn.jio.com/dare_images/shows/2025-11-29/251129561025.jpg"
    },
    {
      "show_name": "Family Food Tales",
      "start_time": "10:50 AM",
      "end_time": "11:00 AM",
      "show_logo": "https://jiotv.catchup.cdn.jio.com/dare_images/shows/2025-11-29/251129561026.jpg"
    },
    {
      "show_name": "Firangi Tadka",
      "start_time": "11:00 AM",
      "end_time": "11:30 AM",
      "show_logo": "https://jiotv.catchup.cdn.jio.com/dare_images/shows/2025-11-29/251129561027.jpg"
    },
    {
      "show_name": "Tea Time",
      "start_time": "11:30 AM",
      "end_time": "12:00 PM",
      "show_logo": "https://jiotv.catchup.cdn.jio.com/dare_images/shows/2025-11-29/251129561028.jpg"
    },
    {
      "show_name": "Mummy Ka Magic",
      "start_time": "12:00 PM",
      "end_time": "12:30 PM",
      "show_logo": "https://jiotv.catchup.cdn.jio.com/dare_images/shows/2025-11-29/251129561029.jpg"
    },
    {
      "show_name": "Winter Treats",
      "start_time": "12:30 PM",
      "end_time": "12:40 PM",
      "show_logo": "https://jiotv.catchup.cdn.jio.com/dare_images/shows/2025-11-29/251129561030.jpg"
    },
    {
      "show_name": "Family Food Tales",
      "start_time": "12:40 PM",
      "end_time": "12:50 PM",
      "show_logo": "https://jiotv.catchup.cdn.jio.com/dare_images/shows/2025-11-29/251129561031.jpg"
    },
    {
      "show_name": "Vegan Vibes",
      "start_time": "12:50 PM",
      "end_time": "01:00 PM",
      "show_logo": "https://jiotv.catchup.cdn.jio.com/dare_images/shows/2025-11-29/251129561032.jpg"
    },
    {
      "show_name": "Cook Smart",
      "start_time": "01:00 PM",
      "end_time": "01:30 PM",
      "show_logo": "https://jiotv.catchup.cdn.jio.com/dare_images/shows/2025-11-29/251129561033.jpg"
    },
    {
      "show_name": "SK Kitchen",
      "start_time": "01:30 PM",
      "end_time": "02:00 PM",
      "show_logo": "https://jiotv.catchup.cdn.jio.com/dare_images/shows/2025-11-29/251129561034.jpg"
    },
    {
      "show_name": "Turban Tadka",
      "start_time": "02:00 PM",
      "end_time": "02:30 PM",
      "show_logo": "https://jiotv.catchup.cdn.jio.com/dare_images/shows/2025-11-29/251129561035.jpg"
    },
    {
      "show_name": "Tea Time",
      "start_time": "02:30 PM",
      "end_time": "03:00 PM",
      "show_logo": "https://jiotv.catchup.cdn.jio.com/dare_images/shows/2025-11-29/251129561036.jpg"
    },
    {
      "show_name": "Mummy Ka Magic",
      "start_time": "03:00 PM",
      "end_time": "03:30 PM",
      "show_logo": "https://jiotv.catchup.cdn.jio.com/dare_images/shows/2025-11-29/251129561037.jpg"
    },
    {
      "show_name": "Cook Smart",
      "start_time": "03:30 PM",
      "end_time": "04:00 PM",
      "show_logo": "https://jiotv.catchup.cdn.jio.com/dare_images/shows/2025-11-29/251129561038.jpg"
    },
    {
      "show_name": "Hi Tea",
      "start_time": "04:00 PM",
      "end_time": "04:30 PM",
      "show_logo": "https://jiotv.catchup.cdn.jio.com/dare_images/shows/2025-11-29/251129561039.jpg"
    },
    {
      "show_name": "Turban Tadka",
      "start_time": "04:30 PM",
      "end_time": "05:00 PM",
      "show_logo": "https://jiotv.catchup.cdn.jio.com/dare_images/shows/2025-11-29/251129561040.jpg"
    },
    {
      "show_name": "Only Veg",
      "start_time": "05:00 PM",
      "end_time": "06:00 PM",
      "show_logo": "https://jiotv.catchup.cdn.jio.com/dare_images/shows/2025-11-29/251129561041.jpg"
    },
    {
      "show_name": "Dairy Delights",
      "start_time": "06:00 PM",
      "end_time": "06:10 PM",
      "show_logo": "https://jiotv.catchup.cdn.jio.com/dare_images/shows/2025-11-29/251129561042.jpg"
    },
    {
      "show_name": "Bake Diaries",
      "start_time": "06:10 PM",
      "end_time": "06:20 PM",
      "show_logo": "https://jiotv.catchup.cdn.jio.com/dare_images/shows/2025-11-29/251129561043.jpg"
    },
    {
      "show_name": "Family Food Tales",
      "start_time": "06:20 PM",
      "end_time": "06:30 PM",
      "show_logo": "https://jiotv.catchup.cdn.jio.com/dare_images/shows/2025-11-29/251129561044.jpg"
    },
    {
      "show_name": "Hi Tea",
      "start_time": "06:30 PM",
      "end_time": "07:00 PM",
      "show_logo": "https://jiotv.catchup.cdn.jio.com/dare_images/shows/2025-11-29/251129561045.jpg"
    },
    {
      "show_name": "Winter Treats",
      "start_time": "07:00 PM",
      "end_time": "07:10 PM",
      "show_logo": "https://jiotv.catchup.cdn.jio.com/dare_images/shows/2025-11-29/251129561046.jpg"
    },
    {
      "show_name": "Vegan Vibes",
      "start_time": "07:10 PM",
      "end_time": "07:20 PM",
      "show_logo": "https://jiotv.catchup.cdn.jio.com/dare_images/shows/2025-11-29/251129561047.jpg"
    },
    {
      "show_name": "Dairy Delights",
      "start_time": "07:20 PM",
      "end_time": "07:30 PM",
      "show_logo": "https://jiotv.catchup.cdn.jio.com/dare_images/shows/2025-11-29/251129561048.jpg"
    },
    {
      "show_name": "Turban Tadka",
      "start_time": "07:30 PM",
      "end_time": "08:00 PM",
      "show_logo": "https://jiotv.catchup.cdn.jio.com/dare_images/shows/2025-11-29/251129561049.jpg"
    },
    {
      "show_name": "Mummy Ka Magic",
      "start_time": "08:00 PM",
      "end_time": "08:30 PM",
      "show_logo": "https://jiotv.catchup.cdn.jio.com/dare_images/shows/2025-11-29/251129561050.jpg"
    },
    {
      "show_name": "Winter Treats",
      "start_time": "08:30 PM",
      "end_time": "08:40 PM",
      "show_logo": "https://jiotv.catchup.cdn.jio.com/dare_images/shows/2025-11-29/251129561051.jpg"
    },
    {
      "show_name": "Family Food Tales",
      "start_time": "08:40 PM",
      "end_time": "08:50 PM",
      "show_logo": "https://jiotv.catchup.cdn.jio.com/dare_images/shows/2025-11-29/251129561052.jpg"
    },
    {
      "show_name": "Vegan Vibes",
      "start_time": "08:50 PM",
      "end_time": "09:00 PM",
      "show_logo": "https://jiotv.catchup.cdn.jio.com/dare_images/shows/2025-11-29/251129561053.jpg"
    },
    {
      "show_name": "SK Kitchen",
      "start_time": "09:00 PM",
      "end_time": "09:30 PM",
      "show_logo": "https://jiotv.catchup.cdn.jio.com/dare_images/shows/2025-11-29/251129561054.jpg"
    },
    {
      "show_name": "Turban Tadka",
      "start_time": "09:30 PM",
      "end_time": "10:00 PM",
      "show_logo": "https://jiotv.catchup.cdn.jio.com/dare_images/shows/2025-11-29/251129561055.jpg"
    },
    {
      "show_name": "Dairy Delights",
      "start_time": "10:00 PM",
      "end_time": "10:10 PM",
      "show_logo": "https://jiotv.catchup.cdn.jio.com/dare_images/shows/2025-11-29/251129561056.jpg"
    },
    {
      "show_name": "Sizzling Dal",
      "start_time": "10:10 PM",
      "end_time": "10:20 PM",
      "show_logo": "https://jiotv.catchup.cdn.jio.com/dare_images/shows/2025-11-29/251129561057.jpg"
    },
    {
      "show_name": "Family Food Tales",
      "start_time": "10:20 PM",
      "end_time": "10:30 PM",
      "show_logo": "https://jiotv.catchup.cdn.jio.com/dare_images/shows/2025-11-29/251129561058.jpg"
    },
    {
      "show_name": "Only Veg",
      "start_time": "10:30 PM",
      "end_time": "11:30 PM",
      "show_logo": "https://jiotv.catchup.cdn.jio.com/dare_images/shows/2025-11-29/251129561059.jpg"
    },
    {
      "show_name": "Cook Smart",
      "start_time": "11:30 PM",
      "end_time": "11:59 PM",
      "show_logo": "https://jiotv.catchup.cdn.jio.com/dare_images/shows/2025-11-29/251129561060.jpg"
    }
  ]
}