{
  "channel_name": "Pogo Hindi",
  "channel_logo": "https://jiotv.catchup.cdn.jio.com/dare_images/images/Pogo_Hindi.png",
  "date": "2025-11-12",
  "programs": [
    {
      "show_name": "Smaashhing Simmba",
      "start_time": "12:00 AM",
      "end_time": "01:00 AM",
      "show_logo": "https://jiotv.catchup.cdn.jio.com/dare_images/shows/2025-11-12/251112559000.jpg"
    },
    {
      "show_name": "Smaashhing Simmba",
      "start_time": "01:00 AM",
      "end_time": "02:00 AM",
      "show_logo": "https://jiotv.catchup.cdn.jio.com/dare_images/shows/2025-11-12/251112559001.jpg"
    },
    {
      "show_name": "Smaashhing Simmba",
      "start_time": "02:00 AM",
      "end_time": "02:12 AM",
      "show_logo": "https://jiotv.catchup.cdn.jio.com/dare_images/shows/2025-11-12/251112559002.jpg"
    },
    {
      "show_name": "Smaashhing Simmba",
      "start_time": "02:12 AM",
      "end_time": "02:24 AM",
      "show_logo": "https://jiotv.catchup.cdn.jio.com/dare_images/shows/2025-11-12/251112559003.jpg"
    },
    {
      "show_name": "Smaashhing Simmba",
      "start_time": "02:24 AM",
      "end_time": "02:36 AM",
      "show_logo": "https://jiotv.catchup.cdn.jio.com/dare_images/shows/2025-11-12/251112559004.jpg"
    },
    {
      "show_name": "Smaashhing Simmba",
      "start_time": "02:36 AM",
      "end_time": "02:48 AM",
      "show_logo": "https://jiotv.catchup.cdn.jio.com/dare_images/shows/2025-11-12/251112559005.jpg"
    },
    {
      "show_name": "Smaashhing Simmba",
      "start_time": "02:48 AM",
      "end_time": "03:00 AM",
      "show_logo": "https://jiotv.catchup.cdn.jio.com/dare_images/shows/2025-11-12/251112559006.jpg"
    },
    {
      "show_name": "Smaashhing Simmba",
      "start_time": "03:00 AM",
      "end_time": "03:12 AM",
      "show_logo": "https://jiotv.catchup.cdn.jio.com/dare_images/shows/2025-11-12/251112559007.jpg"
    },
    {
      "show_name": "Smaashhing Simmba",
      "start_time": "03:12 AM",
      "end_time": "03:24 AM",
      "show_logo": "https://jiotv.catchup.cdn.jio.com/dare_images/shows/2025-11-12/251112559008.jpg"
    },
    {
      "show_name": "Smaashhing Simmba",
      "start_time": "03:24 AM",
      "end_time": "03:36 AM",
      "show_logo": "https://jiotv.catchup.cdn.jio.com/dare_images/shows/2025-11-12/251112559009.jpg"
    },
    {
      "show_name": "Smaashhing Simmba",
      "start_time": "03:36 AM",
      "end_time": "03:48 AM",
      "show_logo": "https://jiotv.catchup.cdn.jio.com/dare_images/shows/2025-11-12/251112559010.jpg"
    },
    {
      "show_name": "Smaashhing Simmba",
      "start_time": "03:48 AM",
      "end_time": "04:00 AM",
      "show_logo": "https://jiotv.catchup.cdn.jio.com/dare_images/shows/2025-11-12/251112559011.jpg"
    },
    {
      "show_name": "Smaashhing Simmba",
      "start_time": "04:00 AM",
      "end_time": "04:12 AM",
      "show_logo": "https://jiotv.catchup.cdn.jio.com/dare_images/shows/2025-11-12/251112559012.jpg"
    },
    {
      "show_name": "Smaashhing Simmba",
      "start_time": "04:12 AM",
      "end_time": "04:24 AM",
      "show_logo": "https://jiotv.catchup.cdn.jio.com/dare_images/shows/2025-11-12/251112559013.jpg"
    },
    {
      "show_name": "Smaashhing Simmba",
      "start_time": "04:24 AM",
      "end_time": "04:36 AM",
      "show_logo": "https://jiotv.catchup.cdn.jio.com/dare_images/shows/2025-11-12/251112559014.jpg"
    },
    {
      "show_name": "Smaashhing Simmba",
      "start_time": "04:36 AM",
      "end_time": "04:48 AM",
      "show_logo": "https://jiotv.catchup.cdn.jio.com/dare_images/shows/2025-11-12/251112559015.jpg"
    },
    {
      "show_name": "Smaashhing Simmba",
      "start_time": "04:48 AM",
      "end_time": "05:00 AM",
      "show_logo": "https://jiotv.catchup.cdn.jio.com/dare_images/shows/2025-11-12/251112559016.jpg"
    },
    {
      "show_name": "Smaashhing Simmba",
      "start_time": "05:00 AM",
      "end_time": "06:00 AM",
      "show_logo": "https://jiotv.catchup.cdn.jio.com/dare_images/shows/2025-11-12/251112559017.jpg"
    },
    {
      "show_name": "Chhota Bheem",
      "start_time": "06:00 AM",
      "end_time": "07:00 AM",
      "show_logo": "https://jiotv.catchup.cdn.jio.com/dare_images/shows/2025-11-12/251112559018.jpg"
    },
    {
      "show_name": "Chhota Bheem",
      "start_time": "07:00 AM",
      "end_time": "07:30 AM",
      "show_logo": "https://jiotv.catchup.cdn.jio.com/dare_images/shows/2025-11-12/251112559019.jpg"
    },
    {
      "show_name": "Chhota Bheem",
      "start_time": "07:30 AM",
      "end_time": "08:30 AM",
      "show_logo": "https://jiotv.catchup.cdn.jio.com/dare_images/shows/2025-11-12/251112559020.jpg"
    },
    {
      "show_name": "Chhota Bheem",
      "start_time": "08:30 AM",
      "end_time": "09:00 AM",
      "show_logo": "https://jiotv.catchup.cdn.jio.com/dare_images/shows/2025-11-12/251112559021.jpg"
    },
    {
      "show_name": "Chhota Bheem",
      "start_time": "09:00 AM",
      "end_time": "09:30 AM",
      "show_logo": "https://jiotv.catchup.cdn.jio.com/dare_images/shows/2025-11-12/251112559022.jpg"
    },
    {
      "show_name": "Jay Jagannath",
      "start_time": "09:30 AM",
      "end_time": "10:30 AM",
      "show_logo": "https://jiotv.catchup.cdn.jio.com/dare_images/shows/2025-11-12/251112559023.jpg"
    },
    {
      "show_name": "Jay Jagannath",
      "start_time": "10:30 AM",
      "end_time": "11:00 AM",
      "show_logo": "https://jiotv.catchup.cdn.jio.com/dare_images/shows/2025-11-12/251112559024.jpg"
    },
    {
      "show_name": "Jay Jagannath",
      "start_time": "11:00 AM",
      "end_time": "11:30 AM",
      "show_logo": "https://jiotv.catchup.cdn.jio.com/dare_images/shows/2025-11-12/251112559025.jpg"
    },
    {
      "show_name": "CB Return Of Karaak",
      "start_time": "11:30 AM",
      "end_time": "12:15 PM",
      "show_logo": "https://jiotv.catchup.cdn.jio.com/dare_images/shows/2025-11-12/251112559026.jpg"
    },
    {
      "show_name": "CB Return Of Karaak",
      "start_time": "12:15 PM",
      "end_time": "01:00 PM",
      "show_logo": "https://jiotv.catchup.cdn.jio.com/dare_images/shows/2025-11-12/251112559027.jpg"
    },
    {
      "show_name": "CB Return Of Karaak",
      "start_time": "01:00 PM",
      "end_time": "02:00 PM",
      "show_logo": "https://jiotv.catchup.cdn.jio.com/dare_images/shows/2025-11-12/251112559028.jpg"
    },
    {
      "show_name": "Little Singham Aur Krishna: Kans Ka Aattank- 1 - Dosti Ki Dor \u0026 Karma Kalash Ki Khoj",
      "start_time": "02:00 PM",
      "end_time": "02:45 PM",
      "show_logo": "https://jiotv.catchup.cdn.jio.com/dare_images/shows/2025-11-12/251112559029.jpg"
    },
    {
      "show_name": "Little Singham Aur Krishna: Kans Ka Aattank Part - 2 - Ritu Patthar \u0026 Santulan Ki Naav",
      "start_time": "02:45 PM",
      "end_time": "03:30 PM",
      "show_logo": "https://jiotv.catchup.cdn.jio.com/dare_images/shows/2025-11-12/251112559030.jpg"
    },
    {
      "show_name": "Little Singham Aur Krishna: Kans Ka Aattank Part - 3 - Surya Nagri \u0026 Laut Aya Kans",
      "start_time": "03:30 PM",
      "end_time": "04:30 PM",
      "show_logo": "https://jiotv.catchup.cdn.jio.com/dare_images/shows/2025-11-12/251112559031.jpg"
    },
    {
      "show_name": "Grizzy and The Lemmings",
      "start_time": "04:30 PM",
      "end_time": "05:00 PM",
      "show_logo": "https://jiotv.catchup.cdn.jio.com/dare_images/shows/2025-11-12/251112559032.jpg"
    },
    {
      "show_name": "Grizzy and The Lemmings: World Tour",
      "start_time": "05:00 PM",
      "end_time": "05:30 PM",
      "show_logo": "https://jiotv.catchup.cdn.jio.com/dare_images/shows/2025-11-12/251112559033.jpg"
    },
    {
      "show_name": "Grizzy and The Lemmings",
      "start_time": "05:30 PM",
      "end_time": "06:00 PM",
      "show_logo": "https://jiotv.catchup.cdn.jio.com/dare_images/shows/2025-11-12/251112559034.jpg"
    },
    {
      "show_name": "Grizzy and The Lemmings",
      "start_time": "06:00 PM",
      "end_time": "06:30 PM",
      "show_logo": "https://jiotv.catchup.cdn.jio.com/dare_images/shows/2025-11-12/251112559035.jpg"
    },
    {
      "show_name": "Mighty Little Bheem",
      "start_time": "06:30 PM",
      "end_time": "07:00 PM",
      "show_logo": "https://jiotv.catchup.cdn.jio.com/dare_images/shows/2025-11-12/251112559036.jpg"
    },
    {
      "show_name": "Mighty Little Bheem",
      "start_time": "07:00 PM",
      "end_time": "07:30 PM",
      "show_logo": "https://jiotv.catchup.cdn.jio.com/dare_images/shows/2025-11-12/251112559037.jpg"
    },
    {
      "show_name": "Mighty Little Bheem",
      "start_time": "07:30 PM",
      "end_time": "08:00 PM",
      "show_logo": "https://jiotv.catchup.cdn.jio.com/dare_images/shows/2025-11-12/251112559038.jpg"
    },
    {
      "show_name": "Mighty Little Bheem",
      "start_time": "08:00 PM",
      "end_time": "08:30 PM",
      "show_logo": "https://jiotv.catchup.cdn.jio.com/dare_images/shows/2025-11-12/251112559039.jpg"
    },
    {
      "show_name": "Lamput",
      "start_time": "08:30 PM",
      "end_time": "09:00 PM",
      "show_logo": "https://jiotv.catchup.cdn.jio.com/dare_images/shows/2025-11-12/251112559040.jpg"
    },
    {
      "show_name": "Lamput",
      "start_time": "09:00 PM",
      "end_time": "09:30 PM",
      "show_logo": "https://jiotv.catchup.cdn.jio.com/dare_images/shows/2025-11-12/251112559041.jpg"
    },
    {
      "show_name": "Lamput",
      "start_time": "09:30 PM",
      "end_time": "10:00 PM",
      "show_logo": "https://jiotv.catchup.cdn.jio.com/dare_images/shows/2025-11-12/251112559042.jpg"
    },
    {
      "show_name": "Lamput",
      "start_time": "10:00 PM",
      "end_time": "10:30 PM",
      "show_logo": "https://jiotv.catchup.cdn.jio.com/dare_images/shows/2025-11-12/251112559043.jpg"
    },
    {
      "show_name": "Chhota Bheem",
      "start_time": "10:30 PM",
      "end_time": "11:00 PM",
      "show_logo": "https://jiotv.catchup.cdn.jio.com/dare_images/shows/2025-11-12/251112559044.jpg"
    },
    {
      "show_name": "Chhota Bheem",
      "start_time": "11:00 PM",
      "end_time": "11:30 PM",
      "show_logo": "https://jiotv.catchup.cdn.jio.com/dare_images/shows/2025-11-12/251112559045.jpg"
    },
    {
      "show_name": "Chhota Bheem",
      "start_time": "11:30 PM",
      "end_time": "11:59 PM",
      "show_logo": "https://jiotv.catchup.cdn.jio.com/dare_images/shows/2025-11-12/251112559046.jpg"
    }
  ]
}