{
  "channel_name": "Sony Max SD",
  "channel_logo": "https://jiotv.catchup.cdn.jio.com/dare_images/images/Sony_Max_SD.png",
  "date": "2025-11-20",
  "programs": [
    {
      "show_name": "Main Hoon Lucky The Racer",
      "start_time": "12:00 AM",
      "end_time": "01:00 AM",
      "show_logo": "https://jiotv.catchup.cdn.jio.com/dare_images/shows/2025-11-20/251120289000.jpg"
    },
    {
      "show_name": "Baadshah Pehlwaan",
      "start_time": "01:00 AM",
      "end_time": "03:15 AM",
      "show_logo": "https://jiotv.catchup.cdn.jio.com/dare_images/shows/2025-11-20/251120289001.jpg"
    },
    {
      "show_name": "Darr @ The Mall",
      "start_time": "03:15 AM",
      "end_time": "05:45 AM",
      "show_logo": "https://jiotv.catchup.cdn.jio.com/dare_images/shows/2025-11-20/251120289003.jpg"
    },
    {
      "show_name": "No Parking (Hindi)",
      "start_time": "05:45 AM",
      "end_time": "08:30 AM",
      "show_logo": "https://jiotv.catchup.cdn.jio.com/dare_images/shows/2025-11-20/251120289005.jpg"
    },
    {
      "show_name": "Firangi",
      "start_time": "08:30 AM",
      "end_time": "11:00 AM",
      "show_logo": "https://jiotv.catchup.cdn.jio.com/dare_images/shows/2025-11-20/251120289007.jpg"
    },
    {
      "show_name": "Firangi",
      "start_time": "11:00 AM",
      "end_time": "02:00 PM",
      "show_logo": "https://jiotv.catchup.cdn.jio.com/dare_images/shows/2025-11-20/251120289009.jpg"
    },
    {
      "show_name": "Pyaar Kiya Nahin Jata",
      "start_time": "02:00 PM",
      "end_time": "04:45 PM",
      "show_logo": "https://jiotv.catchup.cdn.jio.com/dare_images/shows/2025-11-20/251120289011.jpg"
    },
    {
      "show_name": "TE3N",
      "start_time": "04:45 PM",
      "end_time": "07:30 PM",
      "show_logo": "https://jiotv.catchup.cdn.jio.com/dare_images/shows/2025-11-20/251120289013.jpg"
    },
    {
      "show_name": "Badava Rascal",
      "start_time": "07:30 PM",
      "end_time": "09:45 PM",
      "show_logo": "https://jiotv.catchup.cdn.jio.com/dare_images/shows/2025-11-20/251120289015.jpg"
    },
    {
      "show_name": "Rudra Avatar",
      "start_time": "09:45 PM",
      "end_time": "11:59 PM",
      "show_logo": "https://jiotv.catchup.cdn.jio.com/dare_images/shows/2025-11-20/251120289017.jpg"
    }
  ]
}